fakesnake/__init__.py
fakesnake/creation.py
fakesnake/handler.py
fakesnake/main.py
fakesnake/setting.py
fakesnake/core/__init__.py
fakesnake/core/creation.py
fakesnake/core/database.py
fakesnake/utils/__init__.py
fakesnake/utils/creation.py
fakesnake/utils/database.py
fakesnake/utils/util.py
state/__init__.py
state/data.py
state/database.py
fakesnake-0.0.8.dist-info/LICENSE
fakesnake-0.0.8.dist-info/METADATA
fakesnake-0.0.8.dist-info/WHEEL
fakesnake-0.0.8.dist-info/entry_points.txt
fakesnake-0.0.8.dist-info/top_level.txt
fakesnake-0.0.8.dist-info/RECORD
