Metadata-Version: 2.1
Name: fakesnake
Version: 0.0.8
Summary: generate fake data
Home-page: https://github.com/Vin-Cento/fakesnake
Author: Vincent Liu
Author-email: vincentliu362@gmail.com
License-File: LICENSE
Requires-Dist: numpy
Requires-Dist: geopy
Requires-Dist: shapely
Requires-Dist: python-dotenv
Requires-Dist: geojson
Requires-Dist: pyproj
Requires-Dist: click
Requires-Dist: faker
Requires-Dist: rich
